neo4j_advanced_rag/__init__.py
neo4j_advanced_rag/chain.py
neo4j_advanced_rag/retrievers.py
neo4j_advanced_rag-0.1.0.dist-info/METADATA
neo4j_advanced_rag-0.1.0.dist-info/WHEEL
neo4j_advanced_rag-0.1.0.dist-info/RECORD
