Metadata-Version: 2.1
Name: neo4j-advanced-rag
Version: 0.1.0
Summary: Balance precise embeddings and context retention with advanced strategies
Author: Tomaz Bratanic
Author-email: tomaz.bratanic@neo4j.com
Requires-Python: >=3.8.1,<4.0
Classifier: Programming Language :: Python :: 3
Classifier: Programming Language :: Python :: 3.9
Classifier: Programming Language :: Python :: 3.10
Classifier: Programming Language :: Python :: 3.11
Classifier: Programming Language :: Python :: 3.12
Requires-Dist: langchain (>=0.2.14,<0.3.0)
Requires-Dist: langchain-community (>=0.2.12,<0.3.0)
Requires-Dist: langchain-openai (>=0.1.21,<0.2.0)
Requires-Dist: langchain-text-splitters (>=0.2.2,<0.3.0)
Requires-Dist: neo4j (>=5.23.1,<6.0.0)
Requires-Dist: openai (>=1.40.6,<2.0.0)
Requires-Dist: python-dotenv (>=1.0.1,<2.0.0)
Requires-Dist: tiktoken (>=0.7.0,<0.8.0)
